cz_bitbucket_jira_plugin/__init__.py
cz_bitbucket_jira_plugin/defaults.py
cz_bitbucket_jira_plugin/exceptions.py
cz_bitbucket_jira_plugin/functions.py
cz_bitbucket_jira_plugin/main.py
cz_bitbucket_jira_plugin/validators.py
cz_bitbucket_jira_plugin-1.0.0.dist-info/METADATA
cz_bitbucket_jira_plugin-1.0.0.dist-info/WHEEL
cz_bitbucket_jira_plugin-1.0.0.dist-info/entry_points.txt
cz_bitbucket_jira_plugin-1.0.0.dist-info/licenses/LICENSE
cz_bitbucket_jira_plugin-1.0.0.dist-info/RECORD
