Metadata-Version: 2.3
Name: cz-bitbucket-jira-plugin
Version: 1.0.0
Summary: Commitizen plugin that links your Bitbucket commits with your Jira issues
Project-URL: Source, https://github.com/marcosdotme/cz-bitbucket-jira-plugin
Project-URL: Tracker, https://github.com/marcosdotme/cz-bitbucket-jira-plugin/issues
Author-email: Marcos Martins <contato@marcosmartins.me>
License: MIT License
License-File: LICENSE
Keywords: bitbucket,commitizen,commitizen-plugin,conventional-commits,jira
Classifier: Development Status :: 4 - Beta
Classifier: Intended Audience :: Developers
Classifier: License :: OSI Approved :: MIT License
Classifier: Natural Language :: English
Classifier: Operating System :: OS Independent
Classifier: Programming Language :: Python :: 3.10
Classifier: Topic :: Software Development
Classifier: Topic :: Software Development :: Libraries :: Python Modules
Requires-Python: >=3.8
Requires-Dist: commitizen>=3.27.0
Requires-Dist: tomli>=2.0.1
Provides-Extra: dev
Requires-Dist: pytest-xdist>=3.6.1; extra == 'dev'
Requires-Dist: pytest>=8.2.0; extra == 'dev'
Requires-Dist: tox>=4.15.0; extra == 'dev'
